{
  "extends": ["tslint:latest"],
  "rules": {
    "arrow-parens": [true, "ban-single-arg-parens"],
    "interface-name": [true, "never-prefix"],
    "object-literal-sort-keys": false,
    "ordered-imports": [
      true,
      {
        "grouped-imports": true,
        "import-sources-order": "lowercase-first",
        "named-imports-order": "lowercase-first",
        "module-source-path": "full"
      }
    ],
    "variable-name": [
      true,
      "ban-keywords",
      "check-format",
      "allow-leading-underscore",
      "allow-pascal-case"
    ]
  }
}
